{
  "documentoEmitente": "99999999000100",
  "documentoDestinatario": "99999999000147",
  "tipoDocumento": "NFSE",
  "tipoOperacao": "SAIDA",
  "valorTotal": 10.00,
  "dataEmissao": "2011-08-03",
  "municipio": "São Paulo",
  "uf": "SP",
  "nfseNumeroExibicao": "00002701",
  "nfseCodigoVerificacao": "HXBA-6GMC",
  "nfseRazaoEmitente": "INSCRICAO PARA TESTE NFE - PJ/0001",
  "nfseRazaoTomador": "INSCRICAO PARA TESTE NFE - PJ/0001",
  "nfseEnderecoEmitente": "R PEDRO AMERICO 00032, 27 ANDAR - CENTRO - CEP: 01045-010",
  "nfseEnderecoTomador": "R PEDRO AMERICO 00032, 27 ANDAR - CENTRO - CEP: 01045-010",
  "nfseInscricaoMunicipalEmitente": "3.961.999-4",
  "nfseInscricaoMunicipalTomador": "3.961.999-0",
  "nfseDiscriminacao": "teste",
  "nfseEmailTomador": "-----",
  "nfseCodigoServicoTexto": "08567 - Centros de emagrecimento, spa e congêneres.",
  "nfseValorDeducoes": 0,
  "nfseAliquotaIss": 5.00,
  "nfseCreditoIptu": 0,
  "nfseDataVencimentoIss": "2011-09-10"
}
